nextmv_sklearn/__about__.py
nextmv_sklearn/__init__.py
nextmv_sklearn/ndarray.py
nextmv_sklearn/dummy/__init__.py
nextmv_sklearn/dummy/model.py
nextmv_sklearn/dummy/options.py
nextmv_sklearn/dummy/solution.py
nextmv_sklearn/dummy/statistics.py
nextmv_sklearn/ensemble/__init__.py
nextmv_sklearn/ensemble/model.py
nextmv_sklearn/ensemble/options.py
nextmv_sklearn/ensemble/solution.py
nextmv_sklearn/ensemble/statistics.py
nextmv_sklearn/linear_model/__init__.py
nextmv_sklearn/linear_model/model.py
nextmv_sklearn/linear_model/options.py
nextmv_sklearn/linear_model/solution.py
nextmv_sklearn/linear_model/statistics.py
nextmv_sklearn/neural_network/__init__.py
nextmv_sklearn/neural_network/model.py
nextmv_sklearn/neural_network/options.py
nextmv_sklearn/neural_network/solution.py
nextmv_sklearn/neural_network/statistics.py
nextmv_sklearn/tree/__init__.py
nextmv_sklearn/tree/model.py
nextmv_sklearn/tree/options.py
nextmv_sklearn/tree/solution.py
nextmv_sklearn/tree/statistics.py
nextmv_scikit_learn-0.3.3.dist-info/METADATA
nextmv_scikit_learn-0.3.3.dist-info/WHEEL
nextmv_scikit_learn-0.3.3.dist-info/licenses/LICENSE
nextmv_scikit_learn-0.3.3.dist-info/RECORD
