Metadata-Version: 2.4
Name: nextmv-scikit-learn
Version: 0.3.3
Summary: An SDK for integrating scikit-learn with the Nextmv platform
Project-URL: Homepage, https://www.nextmv.io
Project-URL: Documentation, https://nextmv-py.docs.nextmv.io/en/latest/nextmv-scikit-learn/
Project-URL: Repository, https://github.com/nextmv-io/nextmv-py
Author-email: Nextmv <tech@nextmv.io>
Maintainer-email: Nextmv <tech@nextmv.io>
License: # LICENSE
License-File: LICENSE
Keywords: decision engineering,decision science,decisions,gurobi,nextmv,operations research,optimization,solver
Classifier: License :: Other/Proprietary License
Classifier: Operating System :: OS Independent
Classifier: Programming Language :: Python :: 3
Classifier: Programming Language :: Python :: 3.10
Classifier: Programming Language :: Python :: 3.11
Classifier: Programming Language :: Python :: 3.12
Classifier: Programming Language :: Python :: 3.13
Requires-Python: >=3.10
Requires-Dist: nextmv>=0.34.1
Requires-Dist: scikit-learn>=1.6.1
Provides-Extra: dev
Requires-Dist: build>=1.0.3; extra == 'dev'
Requires-Dist: nextmv>=0.25.0; extra == 'dev'
Requires-Dist: pydantic>=2.5.2; extra == 'dev'
Requires-Dist: ruff>=0.1.7; extra == 'dev'
Requires-Dist: scikit-learn>=1.6.1; extra == 'dev'
Requires-Dist: twine>=4.0.2; extra == 'dev'
